secprint-0.1.0.dist-info/METADATA
secprint-0.1.0.dist-info/WHEEL
secprint-0.1.0.dist-info/licenses/LICENSE
secprint/__init__.py
secprint/secprint.py
secprint-0.1.0.dist-info/RECORD
