Metadata-Version: 2.1
Name: secprint
Version: 0.1.0
Summary: Python library to improve console printing by adding context to your prints. It makes your console much cleaner, and you won't have to worry about making your prints beautiful.
Author-Email: Valerian Rey <valerian.rey@gmail.com>, Etienne Bonvin <etienne.bonvin@epfl.ch>
License: MIT
Requires-Python: >=3.8
